{
  "id": "2026-04-05_04-05-生徒からのメッセージを通して再確認した教員の使命と「部活動地域展開事",
  "source_file": "plaud-web:0c0b528beb1dbf950a50b0bd9f4fdc8b",
  "recorded_at": "2026-04-05T02:40:35",
  "ingested_at": "2026-04-12T07:48:52",
  "title": "04-05 生徒からのメッセージを通して再確認した教員の使命と「部活動地域展開事業」への決意",
  "raw": {
    "transcript": "",
    "summary": ""
  },
  "lifelog": {
    "headline": "04-05 生徒からのメッセージを通して再確認した教員の使命と「部活動地域展開事",
    "narrative": "",
    "tags": [
      "plaud"
    ],
    "people": [],
    "locations": [],
    "mood": "",
    "key_points": [],
    "source": "fallback"
  },
  "tasks": [],
  "task_analysis": {
    "total": 0,
    "by_priority": {
      "high": 0,
      "medium": 0,
      "low": 0
    },
    "effort_summary": "(AI 未使用のためタスク抽出はスキップ)",
    "blockers": []
  }
}