{
  "id": "2026-03-30_03-31-協議会議-米国電力需要・aiとデータセンター拡大、電源ポートフォリオ",
  "source_file": "plaud-web:991887d534266533d5fc8ac75389a665",
  "recorded_at": "2026-03-30T22:41:43",
  "ingested_at": "2026-04-12T10:48:22",
  "title": "03-31 協議会議: 米国電力需要・AIとデータセンター拡大、電源ポートフォリオ、送電網課題、政策・投資、学校運営実務",
  "raw": {
    "transcript": "## 1. 米国の電力需要急増とデータセンター拡大\n### 結論\nAI・データセンター拡大により米国の電力需要が急増。PJMでは需要見通しが年0.7%から年4.8%へ上方修正され、約10年で倍増の可能性。増加方向は確実だがスピードは不確実性が高い。\n### 議論ポイント\n1. データセンター由来の需要拡大が主因で地域偏在ありつつ全体は大幅増加\n   - PJMで伸び率が約7倍（2020→2025見通し）\n   - 年4.8%が続けば約10年で倍増\n2. 生成AI普及が電力消費増を加速\n   - 世界のDC電力消費の伸びと生成AI拡大の時期が合致\n3. 先行きは増加だが不確実性が大きい\n   - バブル的拡大の可能性\n   - DCの省エネ進展による単位消費削減余地\n   - AI活用で他部門の省エネが進めば総エネルギー消費は減少の可能性\n## 2. 供給側ボトルネックと電源ポートフォリオ\n### 結論\nビッグテックの拡張速度が供給拡大を上回り電力がボトルネック化。ゼロエミ指向は維持しつつ、逼迫下では原子力・再エネに加え天然ガス・石炭も選択肢として容認。\n### 議論ポイント\n1. 需要増のスピード・スケールが通常の供給増強能力を凌駕\n2. 再エネは変動性と立地不一致が制約、原子力は安定・CO2非排出で関心高い\n3. 短中期の実利志向で化石燃料電源も容認\n4. 技術進展による需要2割削減可能性（2035年までの最大導入前提）も実現度は不透明\n## 3. 電力インフラと送電網拡張の課題\n### 結論\n再エネ供給地点と需要地点のミスマッチ、送電網の老朽化・拡張難、規制や住民反対による遅延が重なり、安定供給とAIなど大口需要の両立が課題。規制緩和の実効性は不透明。\n### 議論ポイント\n1. 送電新設・増強は巨大投資・長期スパンで進捗が遅い\n2. 送電事業の収益性が低く投資インセンティブが弱い\n3. ルート選定への社会的抵抗が強い\n4. 大口需要の自前調達を促すべきとの意見もあり、一般消費者料金上昇懸念\n## 4. 米中のAI・エネルギー競争と政策\n### 結論\nAI覇権と電力供給は連動。中国は石炭主力に再エネ・原子力拡大で迅速対応。米国は政権・州で温度差があり、実利路線（石油・ガス増産）とクリーン推進が併存。供給力拡大が価格安定と競争力維持の鍵。\n### 議論ポイント\n1. 中国は価格競争力と安定供給重視で石炭新増設継続\n2. 米国は「America First」で供給拡大と価格低下・安定を志向、州レベルでクリーン推進\n## 5. テック企業の電源調達行動\n### 結論\nゼロエミ志向ながら逼迫下で柔軟化。既存原子力の電力購入や新設・長期契約への関心が強い一方、再エネの変動性が制約。短期的には天然ガス火力等の活用が現実的。\n### 議論ポイント\n1. 再エネの不安定性・立地不一致が障壁\n2. 原子力は安定・非排出で競争力あり\n3. 逼迫時は非ゼロエミ電源も許容\n## 6. 日米協力と投資見通し（SMR・火力）\n### 結論\nSMRは中長期テーマとして重視。短期は天然ガス火力など化石燃料発電が先行可能。最近の対米投資合意案件にも火力関連が含まれる。\n### 議論ポイント\n1. SMR重視は継続も実用は先\n2. 短期は「まずは火力」で容量確保を優先\n## 7. 系統アクセス・公平性とデータセンター立地\n### 結論\n急増需要で系統逼迫と公平性問題が顕在化。発電所隣接の直供給が進むが、系統サービス料金負担の不公平が制度課題。\n### 議論ポイント\n1. DC向け優先確保が他需要家への配分減少の懸念\n2. 直供給は系統料金を負担しない不公平が論点\n3. 供給・送配電能力不足の全国的議論の高まり\n## 8. 日本のLNG調達と地政学的再編\n### 結論\n米国のLNG輸出倍増見込みを踏まえ、日本は分散・多様化を維持しつつ米国との関係を強化。戦略物資は国産化・同盟国連携で供給網再設計へ。コスト上昇は不可避との認識。\n### 議論ポイント\n1. 米国偏重回避と最適ポートフォリオ構築\n2. 重要鉱物の中国依存低減と安全保障優先で価格上昇容認\n## 9. 学校・地域共同活動の運営・会計・人員\n### 結論\n学校とコミュニティスクール（共同本部）の連携を既存枠組みを基盤に拡張。令和8年度の「千年の企画事業」10万円は書籍・講演会等へ活用し、会計は担当者が責任管理。共同活動関連支出は学校事務局費と県・町事業費を分離管理し、領収書・補助金報告を年度末に整理。旅費助成は別会計で上限目安を運用。委員選定は職場の立場配慮のうえ事務手続き（代理出席・支払い）を標準化。\n### 計画\n- 第2回協議会で来年度連携案を登録・提示\n- 人員重複の負担平準化の役割再配分案作成\n- 予算伝達・会計報告の手順文書化\n- 旅費助成の上限・対象・証憑ルール整備\n- 委員候補一覧と選任基準案の作成、手続SOP整備\n## 10. 実行委員会の前金手続き・備品調達・広報\n### 結論\n県との契約で前金（例：10万円）請求可能な体制を整備し、代表者情報・口座・登録書類（通帳イメージ等）を提出。備品（ホワイトボード・ハンドマイク等）は登録業者へ仕様書付きで一斉見積、未回答は不採用。コミュニティ通信で教科書外学習の情報を町内配布、学校連携で参加促進。\n### 計画\n- 前金請求の様式整備とPDF先行提出＋原本送付\n- 見積期日設定、評価基準と決裁フロー明確化\n- 広報継続、参加アンケートの集計・公開\n## 11. 動物教室・学校備品・検査機材・保険手配\n### 結論\n動物教室は秋（9月最終週・10月土曜）で中学校単位・小学生30名程度を受入。令和7年度備品希望を各校から聴取済みで予算内購入。検査機材（2年生用カメラ等）は相当品で3社見積から選定、10万円前後で計画。各校イベントの保険は人数・期日を明記して年度予算内で手配。\n### 計画\n- 講師日程確定と会場・備品手配\n- 備品購入計画と配分・記録写真再整備\n- 検査機材の比較基準確立と契約\n- 保険の対象イベント一覧と連絡期限設定（例：天馬小9/25）\n## 12. 教育委員会・校内の承認プロセスと運営\n### 結論\n既承認案件の後出し変更は受けず、職員会議でも既承認事実を根拠に対応。関係者の影響度を可視化し、異議への想定問答を準備。資料は最新方針に合わせ再編集し、版管理とレビュー体制を整備。\n### 計画\n- 会議での提示役割・発言順序の事前整理\n- ステークホルダーマッピングと火消し役の割当\n- 明日の資料差替え、チェックリスト導入\n## 13. 部活動の人員配置と外部調整\n### 結論\n島津を担当から外し、職員のメンタル保護を優先。吹奏楽とテニスは分離対応。安保は今年度バスケ部へ、テニス部への参画は見送り。地域展開方針と現場運用の整合性を文書化し、誤解防止のため正式通知フローを整備。\n### 計画\n- 島津外しの正式通知と伝達経路整理\n- 吹奏楽担当体制の再確認とヒアリング\n- テニス部代替支援体制の計画策定\n## 14. 事務・通信・レイアウト・座席配置\n### 結論\n固定電話・内線の不具合により暫定連絡網を整備、電話線敷設と内線配布を急ぐ。座席・机・書類配置の再編でコミュニケーション動線を改善し、3人単位の近接配置を試行。ファイル・機材（テレビタンバー等）は視認性と作業性を両立する再配置が必要。\n### 計画\n- 電話障害の調査・復旧と暫定窓口周知\n- 座席表確定版の共有、ロッカー割当一覧作成\n- 書類の「バケツ事業」分類連携と棚移設\n- 機材置き場と窓口動線の見直し\n## 15. 補助金・決裁・帳票・会計運用\n### 結論\n交付決定済・変更なしは確定伺いで回付。報告は金額帯に応じた決裁区分に従い処理（例：50万円以内は課長止まり、100万円超は副町長）。補助金報告の「鏡（表紙）」様式を整備し、R7→R8へ様式更新とリンク修正。予算執行は1月末までに広告2件含めて完了。\n### 計画\n- 決裁フロー一覧の標準化と周知\n- 鏡ひな型の探索・共有、報告書作成\n- 帳票計算式とリンクの検証・修正\n- 予算消化モニタリングの強化\n## 16. 人員・引き継ぎ・スケジュール調整\n### 結論\n人事異動に伴う挨拶は形式的に、未処理案件の棚卸しと必須処理を優先。体育・施設申請（校外学習届け等）の引き継ぎ先を確定。R6→R8の改修・予算は要件整理が未了。児童クラブは内部増加への受入体制見直しが必要。期日（3/31、12/21、5/15、10日ごろ）の混在を解消し、4–6月の会議・回付を計画通り進行。\n### 計画\n- 引き継ぎ書（電子掲示＋紙決裁）作成と周知\n- 体育・施設関連の担当確定とフロー整理\n- 児童クラブの実態調査と運営体制見直し案\n- 期日一覧の作成と整合、改訂版スケジュール共有\n## 17. 保険・年金・予算科目整理\n### 結論\n厚生年金・健康保険の接続は自動移行を前提に確認。必要に応じ国民年金加入確認。教育費の各科目（研修評価事業、言葉活性化推進事業等）で子ども部分の予算が不足（約25万円）との認識があり、補填策検討が必要。\n### 計画\n- 社会保険の切替状況確認と案内\n- 事業科目別の支出計画再構成と不足分の補填案\n## 18. グローバル意識アップと会議運営\n### 結論\n岩見先生への依頼は済みだが具体日程未確定。3日のALT派遣説明会・担当者会とトライアル説明会の同室開催可否を調整中。資料は昨年度要綱を流用しつつ今年度要件を確認。会議進行ルール\n…(以下略)…",
    "summary": ""
  },
  "lifelog": {
    "headline": "03-31 協議会議: 米国電力需要・AIとデータセンター拡大、電源ポートフォリオ、送電網課題、政策・投資、学校運営実務",
    "tags": [
      "plaud"
    ],
    "source": "raw"
  },
  "tasks": [],
  "task_analysis": {
    "total": 0,
    "by_priority": {
      "high": 0,
      "medium": 0,
      "low": 0
    },
    "effort_summary": ""
  }
}