{
  "id": "2026-05-16_05-16-コーヒー焙煎の失敗分析仮説検証モデルの欠如とプロセス規律の重要性",
  "source_file": "plaud-web:a869820d202255ff2f35a023db0abd13",
  "recorded_at": "2026-05-16T02:24:53",
  "ingested_at": "2026-05-16T21:36:50",
  "title": "05-16 コーヒー焙煎の失敗分析：仮説検証モデルの欠如とプロセス規律の重要性",
  "raw": {
    "transcript": "{\"ai_content\": \"![PLAUD NOTE](permanent/6a96f9e9f528462da5eceab0567a9512/mem_clQakl6qLn/summary_poster/card_20260516055248-v2@132eaa23c3b40e2f91410e-1_20260516055411_47444fbf.png)\\n\\n## コア・シノプシス\\n\\nコーヒー焙煎の検証プロセスは、目標設定の欠如とプロセスの一貫性のなさから、価値ある結論を導き出すことに失敗した。2種類のブラジル豆（「セイハドボネ」と「カルモエステート」）に対する焙煎は、明確な仮説や比較基準なしに、場当たり的な調整を繰り返すだけに終始した。特にカルモエステートの焙煎では、20分を超える極端な時間延長により、フレーバーがフラットになるリスクを認識しながらも、明確な停止基準なくプロセスを続行した。このアプローチは、再現可能な知見を生み出すのではなく、単なる作業ログの域を出ない。我々は、アイスコーヒー向けの苦味と甘みの両立という曖昧な初期目標を掲げたが、それを達成するための具体的なプロファイル設計や評価指標を定義しなかった。その結果、貴重な時間とリソースを費やしたものの、次に繋がる戦略的資産を何も構築できなかった。\\n\\n## 焙煎プロセスの再構築：2つのアプローチの比較分析\\n\\n### 焙煎1：セイハドボネ（深煎り・短期決戦型）\\n*   **目標設定**: アイスコーヒー向けの苦味と甘みの両立を追求。\\n*   **プロセス概要**: 投入温度200℃で開始し、高火力を維持して水抜きを進行。1ハゼ（11分32秒）以降は糖分による焦げ付きを警戒し、火力を絞りつつ風量で温度上昇をコントロール。ニハゼ到達前に焙煎を終了させる計画だったが、結果的にニハゼには至らず、15分56秒で終了。\\n*   **温度推移**:\\n    *   `[00:00]` 投入 (200℃)\\n    *   `[04:00]` 180℃手前\\n    *   `[05:00]` 190℃\\n    *   `[07:00]` 200℃突破\\n    *   `[14:24]` 210℃をキープ\\n*   **結果**: シティロースト程度の煎り上がり。チャフが残り、若干の色ムラが見られるが、豆の膨らみは良好。ベリー系の強い果実味が煙から感じられた。\\n\\n### 焙煎2：カルモエステート（中深煎り・長時間型）\\n*   **目標設定**: 中深煎りを目指す。\\n*   **プロセス概要**: 中点温度150℃から6分で180℃まで戻し、180℃〜190℃のレンジを意図的に長く維持（約10分）。豆の色変化や香りの発現が遅く、ハゼ音の発生まで極端に時間を要した。\\n*   **温度推移**:\\n    *   `[06:00]` 180℃\\n    *   `[08:54]` 180℃〜190℃\\n    *   `[14:45]` 200℃\\n    *   `[20:00]` 20分を超えてハゼ音を確認し、引き上げ。\\n*   **結果**: 17分の時点で「味がフラットになる可能性」を認識。最終的に20分以上をかけてハゼ音を確認し終了。青臭さは消え、パンのような香りを経て甘い香りへと変化した。プロセスが長引きすぎたため、フレーバーの複雑性が失われたリスクが残る。\\n\\n## 戦略的考察：プロセス規律の欠如\\n今回の一連の焙煎は、明確な仮説検証モデルを欠いていた。セイハドボネでは「アイスマンの限界入り」という曖昧な目標を掲げ、カルモエステートでは「ハゼ音が聞こえない」という理由だけでプロセスを20分以上も延長した。これは、望ましい結果を定義し、そこから逆算してプロセスを設計するのではなく、目の前の現象に反応するだけの受動的なアプローチである。これでは再現性のある知見は得られない。今後の焙煎においては、**我々は**目標とする風味特性（酸味、甘味、苦味の具体的なバランス）を数値化し、それを実現するための焙煎プロファイル（時間、温度、火力、風量の計画）を事前に設計し、その計画に対する実績の差異を分析する規律を導入する必要がある。\", \"category\": \"推論の要約\", \"summary_id\": \"20260516055248-v2@132eaa23c3b40e2f91410e-1\", \"summ_type\": \"REASONING-NOTE\", \"summ_type_type\": \"system\", \"original_category\": \"推論の要約\", \"header\": {\"headline\": \"05-16 コーヒー焙煎の失敗分析：仮説検証モデルの欠如とプロセス規律の重要性\", \"keywords\": [], \"industry_category\": null, \"recommend_questions\": null, \"language_code\": null, \"category\": \"\", \"summary_id\": \"\", \"summary_type\": \"\", \"original_category\": null}, \"state\": 10, \"used_template\": {\"template_id\": \"REASONING-NOTE\", \"template_type\": \"official\", \"template_version_id\": \"\"}}",
    "summary": ""
  },
  "lifelog": {
    "headline": "05-16 コーヒー焙煎の失敗分析：仮説検証モデルの欠如とプロセス規律の重要性",
    "tags": [
      "plaud"
    ],
    "source": "raw"
  },
  "tasks": [],
  "task_analysis": {
    "total": 0,
    "by_priority": {
      "high": 0,
      "medium": 0,
      "low": 0
    },
    "effort_summary": "",
    "blockers": []
  }
}