{
  "id": "2026-04-01_04-01-打合せ-地域部活動移行・スポーツ施設運用見直し・青少年協議会再設計・",
  "source_file": "plaud-web:cb34e5c3a24aff831f515ece38931b69",
  "recorded_at": "2026-04-01T07:41:21",
  "ingested_at": "2026-04-12T10:48:22",
  "title": "04-01 打合せ: 地域部活動移行・スポーツ施設運用見直し・青少年協議会再設計・設備対応と人員配分",
  "raw": {
    "transcript": "## 1. 公民館サークルの弱体化と「地域部活動」への移行・初回打合せ設定\n### 結論\n公民館サークルは高齢化・固定化・減少により持続可能性が低下しており、中学生を含む「地域部活動」への段階的移行・連携が必要。4月7日9時半に教育長室で地域展開の第1回打合せを実施し、所管替え後のスケジュールを協議する。\n### 計画\n- [ ] 地域部活動への移行モデルと公民館サークル連携ガイドライン案の作成\n- [ ] 中学校と連携した地域部活動参加時の施設利用メリット（無料・減免）の条件文書化\n- [ ] 公民館サークル現状調査（年齢構成、参加者数、利用頻度）による移行候補の特定\n- [ ] 第1回打合せ（4月7日9時半・教育長室）の招集・出席確認（西本課長・中澤課長）\n### 議論ポイント\n1. 高齢化・固定化・減少で存在意義が問われる。地域展開への移行で持続可能性を確保。\n2. 中学生参加により施設利用の減免・無料化などのメリットが生じる。\n3. 所管替え後の業務負荷増に留意し、関係者の協力が必要。\n## 2. スポーツ施設の申込時期・優先枠・障がい者配慮の見直し\n### 結論\n現行「1ヶ月前の同じ日」申込ルール、健康施設の優先枠、障がい者対応について利用者意見と他施設事例を踏まえた見直しが必要。\n### 計画\n- [ ] 申込ルール・優先枠・障がい者配慮に関する利用者アンケートと他自治体比較\n- [ ] 見直し案（申込期間、優先枠条件、障がい者対応手順）の作成と関係部署協議\n### 議論ポイント\n1. 申込時期「1ヶ月前の同じ日」は再検討が妥当。\n2. 優先枠・障がい者対応が場当たり的で、体系化が必要。\n## 3. テニスコート照明の故障対応（コインタイマー問題）\n### 結論\nコインタイマーの入手困難により、スイッチ式回線への変更で対応する。\n### 計画\n- [ ] コインタイマー撤去とスイッチ式回線への切替工事の実施\n### 議論ポイント\n1. 故障原因はコインタイマーで、現状入手困難。\n2. スイッチ式回線への変更が妥当。\n## 4. 青少年問題協議会のあり方見直し\n### 結論\n従来の非行対策中心の枠組みから、不登校・地域移行・ネット課題など現代的論点へ再設計が必要。法制度の整合性を踏まえ、加古川市の廃止事例を参照しつつ慎重に見直す。\n### 計画\n- [ ] 現行法規・運用のレビューと現代的論点への対応案作成\n- [ ] 「子ども・子育て会議」等との役割分担・連携整理の提案\n### 議論ポイント\n1. 話題は不登校、部活地域移行、ネット問題へシフトし枠組みと乖離。\n2. 法の存在を踏まえ、完全廃止には慎重。\n## 5. 防犯カメラ設置対応\n### 結論\n防犯カメラは設置済で、現状対応は概ね十分。\n### 議論ポイント\n1. 現行設置で安全対策は概ねカバー。\n## 6. 人員増強・減少の混在による「もっと頑張れ」要求と割り振り見直し\n### 結論\n増員に伴う期待値上昇に対応し、成果を示す必要。所管替えや地域展開で業務負荷増が見込まれるため、割り振りの再調整と具体KPIの設定が必要。\n### 計画\n- [ ] 増員に伴う業務割り振り見直し（担当者・負荷調整）\n- [ ] 成果目標（ミュージカル支援、居場所整備、土地取得、コミスク地域展開等）の明文化とKPI設定\n### 議論ポイント\n1. 期待値上昇に応える成果の提示が必要。\n2. 年齢構成の偏りがあり、人的リソースの手当てが課題。\n## 7. 体育館空調室外機付近の駐車場安全対策\n### 結論\n室外機が駐車スペースに近接しているため、中央に輪止めを1基追加し接触リスクを低減する。\n### 計画\n- [ ] 駐車場中央への輪止め追加設置（現場判断で実施）\n### 議論ポイント\n1. 輪止め追加が有効との合意。\n## 8. 桜ウォーキングの開催判断\n### 結論\n近日（明日か明後日）に開催可否を判断し周知する。\n### 計画\n- [ ] 天候等を踏まえた実施可否の判断と周知（明日か明後日）\n### 議論ポイント\n1. 短期的に開催判断が必要。\n## 9. 70周年事業の終了報告と広報\n### 結論\n70周年は終了済だがホームページ等での報告・PRが未整備のため整理して掲出する。\n### 計画\n- [ ] 70周年事業の報告記事作成とホームページ等への掲出・PR\n### 議論ポイント\n1. 当時の掲出不足を踏まえ、再PRが必要。\n## 10. 事務文書規則の改定（4月定例教育委員会）\n### 結論\n4月の定例教育委員会で事務文書規則改定案を上程予定。必要箇所を改める。\n### 計画\n- [ ] 改定案の最終確認と提出準備（4月）\n### 議論ポイント\n1. 改定対象を選定し上程に向け準備中。\n## 11. 会計年度任用職員等への文書回覧・配布管理\n### 結論\n会計年度任用職員への回覧は実施済との報告あり。配布範囲の未確認箇所は継続確認が必要。\n### 議論ポイント\n1. 「会計年度さんは全員回しました」との報告。\n2. 一部資料の回覧範囲が不明で要確認。\n## 12. 4月7日の会議体参加者調整（西本課長の出席）\n### 結論\n第1回のため西本課長にも参加を依頼。施設・文化領域の知見共有と関係団体ネットワーク把握が目的。\n### 計画\n- [ ] 4月7日の会合に西本課長の出席を正式依頼（4月7日）\n### 議論ポイント\n1. 施設・文化領域のアプローチに課長の知見が必要。\n## 13. 電話対応（保留・転送）の運用差異による混乱\n### 結論\n機種差による操作差異が混乱の原因。手順マニュアルの作成・周知が必要。\n### 計画\n- [ ] 現行電話機の保留・転送手順マニュアルの作成・周知\n### 議論ポイント\n1. 機種ごとの操作差異で現場混乱。\n## 14. 来賓・現地対応（南・天満）と挨拶準備\n### 結論\n南は雨天時延期対応。来賓の現地割り当てと挨拶文の準備が必要。部長の現地対応の調整が進行。\n### 議論ポイント\n1. 雨天時の延期と来賓配置の再調整が必要。\n2. 挨拶文の準備が必要。\n## 15. 生涯学習の連絡先（電話番号）の有効性確認\n### 結論\n生涯学習の番号の有効性を確認する必要がある。\n### 議論ポイント\n1. 番号の有効性に関する確認要請あり。\n## 16. 進路・研修関連の依頼と期日整理\n### 結論\n進路フォルダー（R8）と初任研関連資料の確認・送付が必要。流動状況調査の担当者回答期限（4月7日または4月8日）の確定が必要。\n### 計画\n- [ ] 進路フォルダー「R8」の所在確認と資料送付\n- [ ] 研修（初任研）関連資料の確認・整理\n- [ ] 流動状況調査の担当者名回答と提出期限の確定（4月7日/4月8日）\n### 議論ポイント\n1. 進路資料の送付と体系整理が必要。\n2. 期限が迫っており、担当者決定と期日確定が必要。\n## 17. 引き継ぎ書の手続き方法\n### 結論\n引き継ぎ書は押印の上、関係上位者へ提出。インフォメーションからの回覧手順に沿う。提出先と部数の確定が必要。\n### 計画\n- [ ] 引き継ぎ書の押印・提出先（先生・課長・部長）確定\n- [ ] 回覧手順の再確認と部数の確定\n### 議論ポイント\n1. 押印・提出方法の確認が必要。\n2. 提出先・部数の未確定。\n## 18. 消耗品・備品の利用可否（フラットファイル等）とラベリング\n### 結論\n消耗品・ファイル等で使用不可の品が含まれるため、利用可否の明確化とテプラによるラベリング共有が必要。\n### 計画\n- [ ] 使用可能備品リストの整備と禁則品の明示\n- [ ] テプラによる備品ラベリングと共有の継続\n### 議論ポイント\n1. 一部ファイルは使用不可。\n2. 消耗品の範囲明確化が必要。\n3. ラベリングの継続共有。\n## 19. いなチャレロードマップ修正と4月7日の口述書準備\n### 結論\nいなチャレのロードマップを最新化し、4月7日に向けて口述書を準備する。共有手段（「クロード」）の運用は要確認。\n### 計画\n- [ ] ロードマップ修正と口述書作成（4月7日）\n- [ ] 修正版の共有方法・承認フローの確認と実施\n### 議論ポイント\n1. 版管理と共有手順の明確化が必要。\n## 20. 設備・備品の不具合対応（壊れ物、運搬損傷）\n### 結論\n未納品・損傷備品の所在確認と再手配、損傷箇所の清掃・消去で暫定復旧。一括管理外設備（エアコン）は終了処理不要。\n### 計画\n- [ ] 未納品・損傷備品の所在確認、納品状況再確認・再手配\n- [ ] 損傷箇所の清掃・消去の現場対応\n- [ ] 一括管理外設備の運用手順共有\n### 議論ポイント\n1. 運搬時損傷の可能性が高い。\n2. 部分消去・清掃で最低限の復旧は可能。\n## 21. 団体説明・参加促進の方針（協会・保護者連携）\n### 結論\n団体説明会を行い、興味層から段階的に参加を促す。保護者・スタッフの協力体制の不確実性が課題。\n### 計画\n- [ ] 団体説明会の開催と参加希望者募集\n- [ ] 保護者・スタッフの役割分担と協力依頼資料の整備\n### 議論ポイント\n1. 段階的参加が妥当。\n2. 協力体制の説得・合意形成が不足。\n## 22. サッカー協会・地域スポーツ環境（種別構造・天然芝・維持費）\n### 結論\n県の種別構造（1種～3種）や国際基準の天然芝要件が高いハードル。維持管理コストが課題で導入は困難。\n### 議論ポイント\n1. 組織構造の理解共有。\n2. 天然芝導入は維持費の観点で難易度が高い。\n## 23. スケートボード協会の運営課題（役員・費用負担）\n### 結論\n南町の協会は運営負担・費用面で協力獲得が難しく、関係者が誤解されないよう透明性と周知が必要。地域での支援体制構築が重要。\n### 計画\n- [ ] 運営負担・費用の透明化と協力者募集の仕組み整備\n- [ ] 役割・メリットの周知強化と誤解防止のコミュニケーション\n### 議論ポイント\n1. 会長設置の経緯と負担感。\n2. 費用・手続きの煩雑さが障壁。\n## 24. 強化選手支援と施設投資の比較（ななみ選手、室内パーク、照明）\n### 結論\n照明・全天候化等の高コスト投資は効果が見込めるが、段階的整備と費用対効果の評価が必要。選手の練習導線（大阪等）を踏まえた支援策を検討する。\n### 計画\n- [ ] 照明・全天候化の費用試算と投資効果評価（時間短縮、合宿誘致等）\n- [ ] ななみ選手の練習導線と地元施設利用条件のヒアリング\n### 議論ポイント\n1. 高額投資の比較検討（他自治体事例）と合理性評価。\n2. 日々の移動負担と地元設備の活用制約。\n## 25. 会計・アカウント関連の問い合わせ予定\n### 結論\n会計・アカウント関連で確認事項が多数見込まれ、適宜問い合わせる方針。\n### 議論ポイント\n1. 手続き・費用に関する不明点が存在。",
    "summary": ""
  },
  "lifelog": {
    "headline": "04-01 打合せ: 地域部活動移行・スポーツ施設運用見直し・青少年協議会再設計・設備対応と人員配分",
    "tags": [
      "plaud"
    ],
    "source": "raw"
  },
  "tasks": [],
  "task_analysis": {
    "total": 0,
    "by_priority": {
      "high": 0,
      "medium": 0,
      "low": 0
    },
    "effort_summary": "",
    "blockers": []
  }
}