{
  "id": "2026-04-23_04-24-複数話者による雑談、業務報告、専門家解説の記録",
  "source_file": "plaud-web:d3efe95672709f38e8b8cb8991f3e2a6",
  "recorded_at": "2026-04-23T22:04:32",
  "ingested_at": "2026-04-24T21:36:32",
  "title": "04-24 複数話者による雑談、業務報告、専門家解説の記録",
  "raw": {
    "transcript": "{\"ai_content\": \"# 複数話者による雑談、業務報告、専門家解説の記録\\n\\n![PLAUD NOTE](permanent/6a96f9e9f528462da5eceab0567a9512/summary_poster/card_20260423233138-v2@14ba36fbdc0240ecb6a019-1_20260423233350_08ff3f8f.png)\\n\\n本記録は、日常的な雑談から始まり、不動産市場やキャリアに関する専門的な解説、さらには具体的な業務報告とタスク管理へと展開する、多岐にわたる内容を収めている。前半では家庭菜園や食事といった和やかな会話が交わされる一方、中盤以降は不動産投資戦略や働き方の変化に関する深い洞洞、そして担当業務の進捗確認と今後の計画が具体的に語られる。\\n------------\\n## 日常的な雑談と家庭菜園の会話\\n複数の話者による、水槽カバーの購入や食事、家庭菜園の手入れといった日常的な話題が展開された。水槽カバーについては、999円の価格で、直径9cm、高さ25cmの製品が検討されたが、サイズが合わない可能性から再計測が必要との意見が出た。また、水野氏は家庭菜園について専門的な知識を披露。トマトの葉に生えている産毛が、汚れや雑菌を弾いて病気を防ぐバリアの役割を果たしているため、むやみに触らない方が良いと説明した。さらに、ピーマンについては、株全体の成長を優先させるため、最初についた花は摘み取ることが望ましいと語り、植物の成長段階に応じた手入れの重要性を示した。\\n------------\\n## 不動産市場の動向と個人の資産戦略\\n専門家（話者7）が、今後の東京の不動産市場と個人の資産戦略について詳細に解説した。市場は二極化が進み、これまでの東京駅や新宿中心から、品川や羽田空港周辺エリアが新たな中心地として価値を高めると予測。特に品川は、エンターテイメント施設の新設などエリア自体の価値が向上するため、築年数が経過したマンションでも資産価値が維持されやすいと指摘した。また、AIの台頭により単純な事務職の価値が低下する一方、専門技術を持つ人材が集まるエリアの不動産価値は上昇すると分析。会社中心（会社ファースト）の働き方から、個人の生活と働き方を融合させるライフスタイルへと変化する中で、住居選択は重要な戦略となると述べた。50代以降のライフプランとして、都心に住み続けるか、あるいは含み益を確定させて再投資するかなど、個人の価値観に合わせた柔軟な資産形成の必要性を強調した。\\n------------\\n## 事務連絡およびタスクの進捗確認\\n水野氏が自身の担当業務に関する進捗状況と今後の計画を報告した。「点検評価委員会」の資料作成は完了したが、昨日開催された第1回委員会で新たに目次を作成することになり、それに伴い「部活動地域展開推進事業」に関する1ページの追加作成が新たなタスクとして発生した。また、「堀田製薬」へのフォローアップ連絡は完了済みである。今後の計画として、指導者募集のために5月6日を締切としてチラシを配布し、参加者が目標の30人に満たない場合は追加の声かけを行う予定。最終的な参加人数を以て「大塚製薬」の光岡氏へ連絡する段取りとなっている。その他、推進協議会の日程調整（9月開始予定）、リーフレット企画、予約システムの検討（10月に予算決定予定）などが進行中であると共有された。\\n------------\\n## 人生観と働き方に関する考察\\n話者4が中心となり、仕事における満足感と主体性の重要性について自身の考えを述べた。他者から指示された仕事よりも、自身で裁量を持ち、工夫しながら進める「コントロールできる時間」を確保することが、幸福感や満足度に直結すると強調。人によっては困難な課題に挑戦することにやりがいを感じる場合もあるとしつつ、自身は主体性を重視するタイプだと語った。また、40代を目前にして、苦手なことは得意な人に任せ、自分は得意な分野で貢献するという協力関係を築くことの重要性を説いた。若い頃は経験を積むために何でもやる必要があるが、年齢を重ねる中で自分の強みを活かす戦略が賢明であるとの見解を示した。\\n------------\\n## アクションアイテム\\n**@水野**\\n- [ ] 点検評価委員会の新規タスクとして、「部活動地域展開推進事業」に関するページを1ページ作成する - [TBD]\\n- [ ] 「4月28日のスケジュール確認」が何を指すのか、具体的に確認する - [TBD]\\n- [ ] 指導者募集のため、チラシを配布し、5月6日にフォームを締め切る - 2024-05-06\\n- [ ] 募集締切後、参加人数が目標（30人以上）に満たない場合は、指導者へ再度声かけを行う - [TBD]\\n- [ ] 確定した指導者の参加人数を大塚製薬の光岡氏に連絡する - [TBD]\\n- [ ] 「洗面の課題整理」の詰めの作業を完了させる - [TBD]\\n- [ ] 予約システム導入のための見積もりを取得し、10月に予算を決定する - 2024-10-31\", \"category\": \"推論の要約\", \"summary_id\": \"20260423233138-v2@14ba36fbdc0240ecb6a019-1\", \"summ_type\": \"REASONING-NOTE\", \"summ_type_type\": \"system\", \"original_category\": \"推論の要約\", \"header\": {\"headline\": \"04-24 複数話者による雑談、業務報告、専門家解説の記録\", \"keywords\": [], \"industry_category\": null, \"recommend_questions\": null, \"language_code\": null, \"category\": \"\", \"summary_id\": \"\", \"summary_type\": \"\", \"original_category\": null}, \"state\": 10, \"used_template\": {\"template_id\": \"REASONING-NOTE\", \"template_type\": \"official\", \"template_version_id\": \"\"}}",
    "summary": ""
  },
  "lifelog": {
    "headline": "04-24 複数話者による雑談、業務報告、専門家解説の記録",
    "tags": [
      "plaud"
    ],
    "source": "raw"
  },
  "tasks": [],
  "task_analysis": {
    "total": 0,
    "by_priority": {
      "high": 0,
      "medium": 0,
      "low": 0
    },
    "effort_summary": "",
    "blockers": []
  }
}